[
  {
    "id": "red-blue-four-zones",
    "operation": "interpolate_gradient",
    "input": {
      "stops": [
        {
          "r": 255,
          "g": 0,
          "b": 0
        },
        {
          "r": 0,
          "g": 0,
          "b": 255
        }
      ],
      "zones": 4
    },
    "expected": {
      "colors": [
        {
          "r": 255,
          "g": 0,
          "b": 0
        },
        {
          "r": 170,
          "g": 0,
          "b": 85
        },
        {
          "r": 85,
          "g": 0,
          "b": 170
        },
        {
          "r": 0,
          "g": 0,
          "b": 255
        }
      ]
    }
  },
  {
    "id": "red-blue-eight-zones",
    "operation": "interpolate_gradient",
    "input": {
      "stops": [
        {
          "r": 255,
          "g": 0,
          "b": 0
        },
        {
          "r": 0,
          "g": 0,
          "b": 255
        }
      ],
      "zones": 8
    },
    "expected": {
      "colors": [
        {
          "r": 255,
          "g": 0,
          "b": 0
        },
        {
          "r": 219,
          "g": 0,
          "b": 36
        },
        {
          "r": 182,
          "g": 0,
          "b": 73
        },
        {
          "r": 146,
          "g": 0,
          "b": 109
        },
        {
          "r": 109,
          "g": 0,
          "b": 146
        },
        {
          "r": 73,
          "g": 0,
          "b": 182
        },
        {
          "r": 36,
          "g": 0,
          "b": 219
        },
        {
          "r": 0,
          "g": 0,
          "b": 255
        }
      ]
    }
  },
  {
    "id": "four-stops-eight-zones",
    "operation": "interpolate_gradient",
    "input": {
      "stops": [
        {
          "r": 255,
          "g": 0,
          "b": 128
        },
        {
          "r": 124,
          "g": 92,
          "b": 255
        },
        {
          "r": 0,
          "g": 196,
          "b": 255
        },
        {
          "r": 64,
          "g": 224,
          "b": 120
        }
      ],
      "zones": 8
    },
    "expected": {
      "colors": [
        {
          "r": 255,
          "g": 0,
          "b": 128
        },
        {
          "r": 199,
          "g": 39,
          "b": 182
        },
        {
          "r": 143,
          "g": 79,
          "b": 237
        },
        {
          "r": 89,
          "g": 122,
          "b": 255
        },
        {
          "r": 35,
          "g": 166,
          "b": 255
        },
        {
          "r": 9,
          "g": 200,
          "b": 236
        },
        {
          "r": 37,
          "g": 212,
          "b": 178
        },
        {
          "r": 64,
          "g": 224,
          "b": 120
        }
      ]
    }
  },
  {
    "id": "single-stop-repeats",
    "operation": "interpolate_gradient",
    "input": {
      "stops": [
        {
          "r": 124,
          "g": 92,
          "b": 255
        }
      ],
      "zones": 5
    },
    "expected": {
      "colors": [
        {
          "r": 124,
          "g": 92,
          "b": 255
        },
        {
          "r": 124,
          "g": 92,
          "b": 255
        },
        {
          "r": 124,
          "g": 92,
          "b": 255
        },
        {
          "r": 124,
          "g": 92,
          "b": 255
        },
        {
          "r": 124,
          "g": 92,
          "b": 255
        }
      ]
    }
  },
  {
    "id": "one-zone-first-stop",
    "operation": "interpolate_gradient",
    "input": {
      "stops": [
        {
          "r": 255,
          "g": 0,
          "b": 0
        },
        {
          "r": 0,
          "g": 0,
          "b": 255
        }
      ],
      "zones": 1
    },
    "expected": {
      "colors": [
        {
          "r": 255,
          "g": 0,
          "b": 0
        }
      ]
    }
  }
]
