[
  {
    "id": "retroid-pocket-5",
    "friendlyName": "Retroid Pocket 5",
    "android": {
      "model": ["Retroid Pocket 5"],
      "device": ["kona"],
      "led": {
        "driver": "settings_provider",
        "transport": "pserver",
        "colorKey": "joystick_led_light_picker_color",
        "colorFormat": "argb_hex_csv",
        "brightnessKey": "led_light_brightness_percent",
        "brightnessRange": [0.0, 1.0],
        "enableKeys": ["joystick_light_enabled", "left_joystick_light_enabled", "right_joystick_light_enabled"],
        "zones": 2,
        "requiresPermission": null,
        "vendorService": "com.rp.gameassistant"
      }
    },
    "linux": null,
    "capabilities": { "color": true, "brightness": true, "perZone": true },
    "previewCalibration": {
      "saturationScale": 0.98,
      "whiteMix": 0.02,
      "redGain": 1.0,
      "greenGain": 1.0,
      "blueGain": 1.0,
      "valueGamma": 0.9,
      "glowAlpha": 0.28,
      "hueMap": [
        { "input": 0, "output": 0 },
        { "input": 13, "output": 30 },
        { "input": 36, "output": 56 },
        { "input": 60, "output": 60 },
        { "input": 120, "output": 120 },
        { "input": 180, "output": 180 },
        { "input": 240, "output": 240 },
        { "input": 300, "output": 300 },
        { "input": 347, "output": 315 }
      ]
    }
  }
]
